{
  "cycle": 946,
  "run_id": "01KXXH6B90YF85SM60KX1NDSC1",
  "goal": "drain the .evolve/inbox backlog: pick the highest-weight queued todos, implement and ship them one cycle at a time",
  "final_verdict": "PASS",
  "phases": [
    {
      "name": "cycle-recorded",
      "verdict": "PASS",
      "key_findings": "cycle completed; ledger walk deferred to future slice",
      "tokens": {
        "input": 0,
        "output": 0,
        "cache_read": 0,
        "cache_write": 0
      }
    }
  ]
}
